vedirect/__init__.py
vedirect/vedirect.py
vedirect/vedirect_device_emulator.py
vedirect_jmfife-1.0.2.dist-info/LICENSE
vedirect_jmfife-1.0.2.dist-info/METADATA
vedirect_jmfife-1.0.2.dist-info/WHEEL
vedirect_jmfife-1.0.2.dist-info/entry_points.txt
vedirect_jmfife-1.0.2.dist-info/top_level.txt
vedirect_jmfife-1.0.2.dist-info/RECORD
