Metadata-Version: 2.1
Name: vedirect-jmfife
Version: 1.0.2
Summary: Read Victron VEDirect Devices
Home-page: https://github.com/jmfife/vedirect
Author: Mike Fife
Author-email: "J. M. Fife" <jmfife@gmail.com>
Classifier: Programming Language :: Python :: 3
Classifier: License :: OSI Approved :: MIT License
Classifier: Operating System :: OS Independent
Requires-Python: >=3.7
License-File: LICENSE
Requires-Dist: pyserial
